datakeeper/__init__.py
datakeeper/api.py
datakeeper/base.py
datakeeper/datakeeper_app.py
datakeeper/io.py
datakeeper/ipfs.py
datakeeper/msg.py
datakeeper/settings.py
datakeeper/testing.py
datakeeper/utility.py
datakeeper/writers.py
datakeeper/templates/browser.html
datakeeper/templates/component.py
datakeeper/templates/conftest.py
datakeeper/templates/init.py
datakeeper/templates/logging.conf
datakeeper/templates/setup.py
datakeeper/templates/test_component.py
datakeeper-0.0.2.data/scripts/datakeeper_app.py
datakeeper-0.0.2.dist-info/METADATA
datakeeper-0.0.2.dist-info/WHEEL
datakeeper-0.0.2.dist-info/top_level.txt
datakeeper-0.0.2.dist-info/RECORD
